{
  "id": "8bff65a0-6d12-4f06-bcd8-523eb699971b",
  "slug": "chair-whisperers-inc",
  "name": "Chair Whisperers Inc.",
  "type": "business",
  "address": "Unknown location",
  "category": "Shop",
  "description_short": "A unique business in Pjuskeby",
  "description_full": "**[The Establishment]**\n\nChair Whisperers Inc. was founded in 1998 by a group of retired furniture therapists who discovered that chairs in Pjuskeby often harbored secrets and aspirations. The founding members—each a connoisseur of silent furniture conversation—decided they would create a haven for chairs yearning to express their innermost thoughts. Their mission? To translate the subtle murmurs of chair legs and armrests into actionable recommendations for more comfortable and meaningful human interaction with their seated counterparts.\n\nChair Whisperers Inc. specializes in a peculiar art: listening to the quiet yearnings of chairs and crafting bespoke seating adjustments. They offer everything from leg lengthening therapy sessions to upholstery mood readings. Located in an undisclosed corner of Pjuskeby, which only appears when you most need to sit down, the business thrives, albeit enigmatically, within the labyrinthine streets of this whimsical town.\n\n**[The Shop Interior]**\n\nUpon entering Chair Whisperers Inc., patrons find themselves enveloped in an ambiance of tranquil understanding. The air is softly infused with the scent of willow bark tea and a hint of varnish. The interior resembles a cozy cocoon, with chairs of every imaginable make and model positioned expectantly along plush carpets. Each chair awaits its turn to divulge secrets to the attentive staff, seated diligently behind teakwood counters adorned with feather quills and parchment scrolls.\n\nWalls clad in deep, velvety green capture echoes of murmured conversations, offering a comforting hush. The floorboards creak gently, as if sharing their own stories of the feet that have treaded before. The shop's centerpiece is an antique, circular podium known as the \"Discourse Disc\" where chairs are invited to divulge their tales to the skilled artisans.\n\n**[Signature Products/Services]**\n\nChair Whisperers Inc. is best known for its \"Seat-Soul Synchronization\" service, priced at a modest 250 kroner. This remarkable process involves a delicate communication session between the chair and its owner, aligning their energies for optimal comfort and mutual benefit.\n\nOther notable services include the \"Armrest Affirmation\" therapy, where armrests are encouraged to express their supportive nature, and the \"Leg Limbering Ritual,\" which ensures maximum stability for those more wobbly chairs. For 100 kroner, patrons can enjoy a \"Cushion Consultation,\" which helps cushions find their true purpose, whether it be firmness, fluffiness, or existential softness.\n\n**[The Clientele]**\n\nThe clientele of Chair Whisperers Inc. is as eclectic as the business itself. Visitors range from local artisans seeking inspiration, to philosophical academics pondering the existential significance of sitting. Families often come to have their heirloom chairs' stories deciphered, while adventurous tourists stumble upon the establishment as they explore Pjuskeby's peculiar alleyways.\n\nEach customer is treated with the same respect as the chairs themselves, their presence adding an extra layer of intrigue to the already vibrant tapestry of the shop. The clientele is bound by a shared curiosity—a desire to understand the thoughts of inanimate companions.\n\n**[Business Philosophy]**\n\nAt the heart of Chair Whisperers Inc. lies a simple yet profound philosophy: every chair has a story to tell, and every sitter deserves to hear it. The business believes that harmonious interaction between people and furniture enriches lives and elevates the mundane act of sitting into a meaningful experience.\n\nThey maintain that a chair's comfort is directly proportional to how intimately it has been listened to, and that a well-heard chair is a happier, more accommodating chair. Thus, they see their work not merely as a business but as an art form—a way to bridge the gap between furniture and its human companions.\n\n**[Local Reputation]**\n\nIn Pjuskeby, Chair Whisperers Inc. occupies a space between legend and beloved eccentricity. Townspeople speak of it in whispers, often referring to it as the place where their grandmother's rocking chair found its voice. It is said that even the most stoic of chairs has wept tears of gratitude after a session here.\n\nRumor has it that Pjuskeby's mayor once consulted the establishment before purchasing new chairs for the town hall. The mayor insisted that the chairs be of sound mind to prevent them from developing \"political aspirations\" during council meetings.\n\nBUSINESS_KEYWORDS=chair care, furniture therapy, upholstery adjustment, seating consultation, chair secrets  \nCONTACT_INFO=Slip a note under the third pebble from the left on the main road  \nOPENING_HOURS=Mon-Sat: When the moon is full|Sundays: Closed for chair choir practice|Tuesdays: Open if your name starts with \"J\"  \nSTATISTICS=Chairs Whispered:2567|Secrets Revealed:973|Satisfied Seats:1842|Ghost Chairs Appeared:12  \nFUN_FACTS=Once a chair recited poetry|Owner's cat can read hieroglyphs|Shop only appears in fog|Chairs sing at midnight|Founder was once a chair himself",
  "specialties": [],
  "established": "Unknown",
  "business_keywords": "chair care, furniture therapy, upholstery adjustment, seating consultation, chair secrets  ",
  "contact_info": "Slip a note under the third pebble from the left on the main road  ",
  "opening_hours": [
    "Mon-Sat: When the moon is full",
    "Sundays: Closed for chair choir practice",
    "Tuesdays: Open if your name starts with \"J\"  "
  ],
  "statistics": [
    {
      "label": "Chairs Whispered",
      "value": "2567"
    },
    {
      "label": "Secrets Revealed",
      "value": "973"
    },
    {
      "label": "Satisfied Seats",
      "value": "1842"
    },
    {
      "label": "Ghost Chairs Appeared",
      "value": "12"
    }
  ],
  "fun_facts": [
    "Once a chair recited poetry",
    "Owner's cat can read hieroglyphs",
    "Shop only appears in fog",
    "Chairs sing at midnight",
    "Founder was once a chair himself"
  ]
}