{
  "id": "40d3e316-acab-46f1-9758-8225a4be484e",
  "slug": "crankle-bop",
  "name": "Crankle & Bop",
  "type": "business",
  "address": "Unknown location",
  "category": "Shop",
  "description_short": "A unique business in Pjuskeby",
  "description_full": "**[The Establishment]**\n\nCrankle & Bop is Pjuskeby’s most delightfully obscure establishment, operating on that peculiar edge of reality where whimsy and mechanics kiss awkwardly. Founded somewhat accidentally in 1957 by Astrid Crankle, an enchantingly unreliable inventor, and her taciturn partner Oliver Bop, who may or may not exist outside the hours of 3 PM to 4 PM on Thursdays, Crankle & Bop was born from a moment of divine mechanical inspiration—or perhaps a minor explosion involving clock gears and goose feathers. \n\nNestled at an undisclosed location known only to those who seek it with a heart full of wonder and a pocket full of mismatched screws, Crankle & Bop specializes in the repair and creation of improbable devices. These include but are not limited to, sentient cuckoo clocks, self-buttering toast contraptions, and levitating teacup sets. Astrid insists the shop's ability to remain undiscovered by the unwary is a feature, not a bug, citing a pact with the local gnomes as the cause.\n\n**[The Shop Interior]**\n\nEntering Crankle & Bop feels much like stepping into a mechanical forest where the trees are made of intricate brass machinery and the leaves whisper secrets in the language of gears and springs. The air hums with a gentle, clockwork symphony, punctuated by the soft ticking of timepieces and the occasional whoosh of something inexplicably floating past. Shelves sag softly beneath the weight of curious instruments, some of which appear to be in the process of inventing themselves.\n\nThe walls are adorned with mismatched timepieces and framed blueprints of inventions that range from the whimsical to the downright absurd—a blueprint for a \"Tea-Serving Octopus\" sharing wall space with a \"Snoring Silencer\". A small, perpetually steaming samovar named Gustav resides in the shop's corner, graciously serving hot herbal concoctions to patrons with a penchant for mechanical musings.\n\n**[Signature Products/Services]**\n\nCrankle & Bop's most celebrated offering is the \"Curious Cogwheel Consultations,\" an enigmatic experience where patrons bring their most perplexing mechanical dilemmas, and leave with solutions that defy conventional logic yet work like a charm. A favorite among locals is the shop’s line of \"Whimsy Watches,\" timepieces that not only tell you the hour but also offer unsolicited philosophical advice at quarter past the hour, including gems like \"Tick, but don't tock too hard.\"\n\nAnother signature service is the \"Gadget Guardian Program,\" where you can leave your cherished mechanical companion with the shop for periodic tune-ups or existential discussions—because every toaster deserves an occasional heart-to-gearheart chat. Prices are negotiable, often determined by the phase of the moon, and occasionally by the temperament of Astrid’s cat, Crankle, who believes himself the true proprietor.\n\n**[The Clientele]**\n\nThe clientele of Crankle & Bop is as eclectic as the shop itself, comprising local tinkers, curious tourists, and the occasional wayward pixie in need of a good oiling. Regulars include Olav Oakenboot, who swears by their \"self-replenishing socks,\" and Ingrid Dimplenook, who consults the shop for her biannual \"Kettle Counseling.\"\n\nVisitors are encouraged to leave with more questions than they arrived with, and many find themselves drawn back by the promise of further delightful confusions and unorthodox solutions. It’s not uncommon to find a group of patrons gathered around a rogue vacuum cleaner philosophizing in tongues unknown, or observing the synchronized dance of the singing spoons.\n\n**[Business Philosophy]**\n\nCrankle & Bop operates on a business philosophy that can best be described as “rhythmic serendipity”—a belief that everything in the universe has a clockwork heart waiting to be discovered. The staff (who are rarely visible, yet always present) encourage patrons to embrace the unpredictable and trust the cogs of fate to click into place.\n\nThe shop’s manifesto is summed up by a sign that somehow translates itself to suit the reader: “Herein lies the magic of perhaps, where certainty is but a suggestion.” It’s a place where the absurd is celebrated, and the mundane is gently nudged aside to reveal the wonders beneath.\n\n**[Local Reputation]**\n\nIn Pjuskeby, Crankle & Bop is revered as a bastion of joyful unpredictability. Some say the shop is blessed by the clockwork spirits, while others attribute its renown to the persistent rumor of an invisible door that leads to a dimension where inventors enjoy high tea with their inventions.\n\nLocals affectionately refer to the establishment as “The Mechanical Menagerie” and proudly share tales of devices that inexplicably fix themselves after a visit. It’s said that those who manage to find the shop and leave with a purchase are bound to experience a serendipitous event within the fortnight.\n\nAstrid Crankle, enigmatic and ever-smudged with oil, is hailed as Pjuskeby’s unofficial ambassador of absurdity, and many swear by her ability to balance the most intricate of mechanical ballets with little more than her imagination and a well-placed spanner.\n\n---\n\nBUSINESS_KEYWORDS=mechanical repairs, whimsical gadgets, clockwork, invention, peculiar devices, gadget maintenance, philosophical timepieces  \nCONTACT_INFO=Whisper to the wind|Consult the third owl on Featherwood Street|Tap your foot thrice in the square  \nOPENING_HOURS=Mon-Fri: When the shadows tickle noon|Weekends: By appointment with destiny|Tuesdays: Closed for clockwork contemplation  \nSTATISTICS=Strange Device Fixes:72|Inexplicable Levitations:16|Tea Served:453|Unscheduled Sing-alongs:29  \nFUN_FACTS=Shop was once a temporary home for a traveling circus|Watch out for the talking gramophone|Won Pjuskeby's 'Most Unlikely Store' award twice|Astrid once built a birdhouse that attracted clouds|Gustav the samovar was elected chair of the local garden gnome council",
  "specialties": [],
  "established": "Unknown",
  "business_keywords": "mechanical repairs, whimsical gadgets, clockwork, invention, peculiar devices, gadget maintenance, philosophical timepieces  ",
  "contact_info": "Whisper to the wind|Consult the third owl on Featherwood Street|Tap your foot thrice in the square  ",
  "opening_hours": [
    "Mon-Fri: When the shadows tickle noon",
    "Weekends: By appointment with destiny",
    "Tuesdays: Closed for clockwork contemplation  "
  ],
  "statistics": [
    {
      "label": "Strange Device Fixes",
      "value": "72"
    },
    {
      "label": "Inexplicable Levitations",
      "value": "16"
    },
    {
      "label": "Tea Served",
      "value": "453"
    },
    {
      "label": "Unscheduled Sing-alongs",
      "value": "29"
    }
  ],
  "fun_facts": [
    "Shop was once a temporary home for a traveling circus",
    "Watch out for the talking gramophone",
    "Won Pjuskeby's 'Most Unlikely Store' award twice",
    "Astrid once built a birdhouse that attracted clouds",
    "Gustav the samovar was elected chair of the local garden gnome council"
  ]
}