{
  "id": "676f2035-a230-4bff-98ef-a719a6194d2c",
  "slug": "granny-s-sneezing-powder-emporium",
  "name": "Granny's Sneezing Powder Emporium",
  "type": "business",
  "address": "Unknown location",
  "category": "Shop",
  "description_short": "A unique business in Pjuskeby",
  "description_full": "**[The Establishment]**\n\nGranny's Sneezing Powder Emporium is not so much a shop as it is a swirling vortex of enchanting aromas and unexpected tickles—if you can find it, that is. Nestled somewhere within the misty folds of Pjuskeby, it defies any map or logical direction, appearing only when it senses a particularly curious sneeze from a passerby or an unusually chilly gust of wind. Founded by the mysterious Granny Bjorndottir, rumored to be older than the fjords themselves, the emporium began as a modest experiment in botanic mischief when Granny discovered the volatile properties of snoring mushrooms and giggleberries. \n\nOne autumn night, as the town's fog clung to the streets like a sleepy duvet, Granny mixed her first batch of sneezing powder. The result was a delightful concoction that made everyone who inhaled it sneeze out tiny, harmless puffs of delight—so infectious that even the stoic seagulls of Pjuskeby lost their composure and chuckled for hours. Word of Granny's magical creation spread like dandelion wishes on the wind, and thus, the Sneezing Powder Emporium found its place in local lore.\n\n**[The Shop Interior]**\n\nStepping into Granny's Sneezing Powder Emporium is akin to walking into a kaleidoscope of fragrances. The air is alive with hints of cinnamon giggles and peppermint sighs, all swirling above shelves that seem to stretch into invisible ceilings. The walls are lined with jars of every imaginable color, each labeled in Granny's loopy handwriting with names like \"Chortleberry Blast\" and \"Hiccoughing Hibiscus.\" \n\nThe floor creaks beneath visitors' feet, echoing the groans of an ancient sea monster who's just realized it's in the wrong ocean. The shop's centerpiece is a gargantuan sneezeberry tree that grows through the middle of the floor—a living testament to Granny's green-thumbed sorcery. Its branches are perpetually dusted with magical pollen, providing customers an impromptu sneeze as they peruse the stock.\n\n**[Signature Products/Services]**\n\nThe Emporium's pièce de résistance is, unsurprisingly, the sneezing powders. The most popular variant, \"Sunlit Sneeze,\" is famed for its ability to invoke a sunny disposition in even the grumpiest troll. At 33 kroner per jar, it promises a day full of gentle sneezes that dissipate any clouds above your head. For the bold adventurer, there's \"Avalanche Alarum,\" guaranteeing a thunderous sneeze that could wake a hibernating bear—or at least your cat.\n\nBesides sneezing powders, the Emporium also houses a selection of enchanted handkerchiefs woven with eldritch threads that change color based on your mood. For those in need of a little chaos, \"Pandemonium Perfume\" releases a scent so bewilderingly charming that it causes flowers to bloom out of season and fish to hum their favorite shanties.\n\n**[The Clientele]**\n\nGranny's Sneezing Powder Emporium attracts an eclectic mix of patrons. Local witches frequent the shop early in the mornings, purchasing sneezing powders in bulk for an array of spells—both benign and mischievous. Barnacle-bearded fishermen from the nearby coast pop in to secure a jar of \"Winter Whale Sneeze,\" which is said to bring good luck and a bountiful catch.\n\nCuriously, the emporium is also a popular destination for the town's librarians, who have taken to sprinkling \"Dustless Delight\" on aging tomes to ensure readers are met with only the freshest whiffs of history. Children, mischievous sprites that they are, can often be found giggling in the aisles, dreaming up pranks that their nannies will inevitably frown upon.\n\n**[Business Philosophy]**\n\nGranny's business philosophy hinges on the belief that a sneeze is far more than a mere expulsion of air; it's an opportunity for laughter and connection. She has always said, \"A sneeze shared is a smile squared,\" and so she dedicates herself to crafting powders that transform the mundane into magic. \n\nThe emporium runs on a simple honesty system—there's no register, just a patina'd brass bell that tinkles approvingly when the correct amount is deposited into a tiny wishing well. Granny believes in the inherent goodness of sneezers everywhere, trusting that the joy her powders bring will be recompensed in full, with laughter as interest.\n\n**[Local Reputation]**\n\nPjuskeby townsfolk speak of the Sneezing Powder Emporium with a mix of reverence and delight. It's said that no one ever really \"plans\" a trip there—rather, the shop finds them when they're in need of a good chuckle or a serendipitous sneeze. The legend goes that if you try too hard to find it, the emporium will simply remain hidden, like a shy cat entwined with invisibility.\n\nFor years, tales of Granny's sneezes have floated through the cobblestones of Pjuskeby, woven into the fabric of local folklore. \"Never trust a serious sneeze,\" the elders whisper to the younger generations, \"for it surely comes from someone who hasn't visited Granny's in too long.\"\n\nBUSINESS_KEYWORDS=sneezing powders, enchanted handkerchiefs, laughter potions, magical supplies, mystical fragrances\nCONTACT_INFO=Contact by releasing a sneeze butterfly|Send a puff of laughter into the wind|Visit when the moon giggles\nOPENING_HOURS=Mon-Fri: When the wind is ripe|Weekends: When the sneezeberry blooms|Tuesdays: Closed for giggle harvest\nSTATISTICS=Sneezes Per Day: 112|Sneeze-Induced Giggles: 74|Vanishing Customers: 3|Invisible Footprints:12\nFUN_FACTS=Shop moves on Tuesdays|Sneezes recorded for research|Jars spontaneously rearrange themselves|Granny never seen at the same time twice|Accepts payment in chuckles",
  "specialties": [],
  "established": "Unknown",
  "business_keywords": "sneezing powders, enchanted handkerchiefs, laughter potions, magical supplies, mystical fragrances",
  "contact_info": "Contact by releasing a sneeze butterfly|Send a puff of laughter into the wind|Visit when the moon giggles",
  "opening_hours": [
    "Mon-Fri: When the wind is ripe",
    "Weekends: When the sneezeberry blooms",
    "Tuesdays: Closed for giggle harvest"
  ],
  "statistics": [
    {
      "label": "Sneezes Per Day",
      "value": "112"
    },
    {
      "label": "Sneeze-Induced Giggles",
      "value": "74"
    },
    {
      "label": "Vanishing Customers",
      "value": "3"
    },
    {
      "label": "Invisible Footprints",
      "value": "12"
    }
  ],
  "fun_facts": [
    "Shop moves on Tuesdays",
    "Sneezes recorded for research",
    "Jars spontaneously rearrange themselves",
    "Granny never seen at the same time twice",
    "Accepts payment in chuckles"
  ]
}