{
  "id": "66876611-58ee-4c6f-b55b-f2b5047980e8",
  "slug": "moody-gnome-studios",
  "name": "Moody Gnome Studios",
  "type": "business",
  "address": "Unknown location",
  "category": "Shop",
  "description_short": "A unique business in Pjuskeby",
  "description_full": "**[The Establishment]**\n\nNestled in one of Pjuskeby's less-traveled fjord paths, Moody Gnome Studios is a fantastical establishment where creativity and clocks tick in harmonious discord. Officially founded in 1978 by an eccentric horologist named Lillith Fjordskip, Moody Gnome Studios was born out of a peculiar incident involving a misplaced sundial and a disgruntled gnome who bargained his way into becoming the muse of all its creations. Specializing in whimsical timepieces, the studio masterfully blends woodcraft with the secretive arts of gnome enchantments, offering Pjuskeby's residents a taste of temporal wonder.\n\nThe exact location of the studio is as elusive as a Norwegian fog, constantly shifting like the tides of time themselves. Residents must follow the cryptic directions etched into the cobblestones that only appear under the moon's persuasive gaze, or listen for the melodious tick-tock symphony that echoes through the mist. Once found, Moody Gnome Studios is a portal to a world where time is anything but linear, and every clock tells a story interwoven with gnome-ish whispers.\n\n**[The Shop Interior]**\n\nStepping inside Moody Gnome Studios is akin to entering a realm where time stands still just long enough to wink at you before rushing on. The walls are a kaleidoscope of polished timbers and glass, displaying clocks of every conceivable design—each pulsating with the soft glow of captured moonlight. A peculiar scent of pine and cinnamon lingers in the air, possibly from the incense burned by Lillith as an offering to the gnome spirits residing within the gears and springs.\n\nThe shop floor is a curious labyrinth of ticking marvels: grandfather clocks that chime with the laughter of midnight revelers, cuckoo clocks featuring tiny gnomes with varying degrees of impatience, and pocket watches that occasionally burp when wound too tight. At the center stands the Enigma Clock, a grand, brass-bezeled timepiece which allegedly holds the secret to the lost hour of 1932—a well-known enigma among Pjuskeby historians. \n\nDespite its apparent clutter, the shop exudes an inexplicable sense of order, as if every cog and pendulum knows exactly where it belongs in the grand dance of time.\n\n**[Signature Products/Services]**\n\nMoody Gnome Studios is renowned for its bespoke timepieces, each accompanied by a spirited origin tale. The shop's signature piece, the “Whimsical Whirligig,” is a must-have for any Pjuskeby household. This handcrafted mantel clock not only tells time but also forecasts local weather with the rise and fall of its miniature gnome inhabitants, known to grumble ahead of rain and sunbathe in periods of prolonged sunshine. Priced at 134 kroner, it’s a steal for a day's worth of accurate prognostication.\n\nFor those seeking something outlandishly personal, the studio offers custom gnome-engraved sundials that reflect not the sun's passage, but the owner's own mood. On particularly gloomy days, the sundials have been known to dispense solace in the form of cryptic yet comforting gnome proverbs.\n\nThe studio also houses a repair service where time-troubled folks can bring their erratic clocks. Lillith, with her deft hands and gnome-guided intuition, restores each one to its rightful rhythm. Repairs are priced according to the clock's disposition—docile timepieces at a modest 43 kroner, while those with a grumpy demeanor might incur a 'gnome handling fee.'\n\n**[The Clientele]**\n\nMoody Gnome Studios attracts a peculiar mix of patrons. Local tinkerers eager to learn the secrets of gnome-infused mechanics frequent the shop, often leaving with more questions than answers. Pjuskeby's artistic elite visit to commission surreal timepieces that challenge the very notion of temporal reality.\n\nThe most devoted client is undoubtedly Herr Millstone, the town’s unofficial horologist and avid collector of unusual clocks. He visits on a weekly basis, accompanied by his pet hedgehog, Time-bert, who, despite his name, appears utterly uninterested in anything but the shop’s assortment of chewy wood shavings.\n\nOn occasion, curious tourists from far-flung lands stumble upon the shop by chance, often leaving with a peculiar tick in their step and a clock they cannot quite recall buying.\n\n**[Business Philosophy]**\n\nThe philosophy at Moody Gnome Studios is simple yet profoundly complex: Time is a dance best accompanied by mischief and mystery. Lillith and her gnome companions believe that every creation should evoke both wonder and whimsy, leaving customers enchanted by the unpredictable yet comforting tick-tock of life’s journey.\n\nThe studio operates under the guiding principle that each clock reflects its owner’s spirit. As such, Lillith insists on a brief but profoundly odd conversation with customers to ensure their eccentricities are perfectly captured within their timepiece.\n\n**[Local Reputation]**\n\nIn Pjuskeby, Moody Gnome Studios is regarded less as a business and more as an institution of delightful oddities. Townsfolk speak of it with reverence and a touch of bemusement, sharing tales of clocks that once held entire conversations with their owners or dispensed sage advice through the subtlety of their chimes.\n\n“Moody Gnome? Ah, it’s where time forgets itself and remembers you instead,” chuckles Old Man Fiddlesticks, the town’s unofficial storyteller, who claims the clocks there once whispered the location of a lost sock of his, and never speak of it again.\n\nTo locals, the studio is both an enigma and a beacon—a place where time is an unreliable narrator and gnomes are the storytellers of ages.\n\nBUSINESS_KEYWORDS=whimsical timepieces, gnome enchantments, bespoke clocks, mood sundials, clock repairs\nCONTACT_INFO=Listen for the tick-tock symphony at midnight\nOPENING_HOURS=Mon-Fri: When gnomes wake|Sat: Just before the moon winks|Sun: Whenever time takes a coffee break\nSTATISTICS=Gnomish Apparitions:12|Lost Hours Restored:5|Laughing Clocks:43|Sundial Mood Swings:9\nFUN_FACTS=Clocks tick counterclockwise on Wednesdays|Once sold a clock to a passing narwhal|Gnomes demand one sock as payment|Winner of 'Most Punctual' award at Pjuskeby's annual fair|Has a resident ghost who detests digital watches",
  "specialties": [],
  "established": "Unknown",
  "business_keywords": "whimsical timepieces, gnome enchantments, bespoke clocks, mood sundials, clock repairs",
  "contact_info": "Listen for the tick-tock symphony at midnight",
  "opening_hours": [
    "Mon-Fri: When gnomes wake",
    "Sat: Just before the moon winks",
    "Sun: Whenever time takes a coffee break"
  ],
  "statistics": [
    {
      "label": "Gnomish Apparitions",
      "value": "12"
    },
    {
      "label": "Lost Hours Restored",
      "value": "5"
    },
    {
      "label": "Laughing Clocks",
      "value": "43"
    },
    {
      "label": "Sundial Mood Swings",
      "value": "9"
    }
  ],
  "fun_facts": [
    "Clocks tick counterclockwise on Wednesdays",
    "Once sold a clock to a passing narwhal",
    "Gnomes demand one sock as payment",
    "Winner of 'Most Punctual' award at Pjuskeby's annual fair",
    "Has a resident ghost who detests digital watches"
  ]
}