{
  "id": "abf55521-0a8a-4805-af3b-99f917e6dd54",
  "slug": "pants-philosophy",
  "name": "Pants & Philosophy",
  "type": "business",
  "address": "Unknown location",
  "category": "Shop",
  "description_short": "A unique business in Pjuskeby",
  "description_full": "**[The Establishment]**\n\nNestled somewhere within the birch-laden folds of Pjuskeby, where the air carries whispers of cinnamon and misplaced logic, lies Pants & Philosophy—a peculiar establishment defying both navigation and expectation. Founded, as legend insists, by Ingulf Snusflatt in a serendipitous moment of enlightenment while wearing mismatched trousers, it purveys an unparalleled blend of legwear and existential inquiry. Ingulf, notorious for his introspective rambles through the fjords, once realized that the true meaning of life may indeed reside between the seams of a well-fitted pant. Since that revelation in 1976, Pants & Philosophy has offered its eclectic wares to those possessing a similarly whimsical disposition—or simply to those who manage to find it.\n\nThe shop’s exact location remains a delightful enigma, moving slightly each week as if in conversation with the earth. This peculiar habit is attributed to the presence of enchanted lint that guides the store’s foundations in a perpetual dance around Pjuskeby. Locals claim that the shop only reveals itself to those in possession of a curious heart and two odd socks in their pocket.\n\n**[The Shop Interior]**\n\nUpon entering Pants & Philosophy, one is immediately enveloped in an atmosphere that can only be described as a mélange of sartorial eccentricity and philosophical pondering. The walls, painted an ever-shifting hue reminiscent of the Northern Lights, play host to shelves upon shelves of trousers, each accompanied by a corresponding philosophical tract. From corduroy to canvas, every fabric invites reflection. The trousers hang languidly beneath overhead mobiles of spinning orbs, representing the celestial spheres pondered by philosophers of old.\n\nA peculiar rotary telephone, its cord forever tangled in deep thought, sits atop the sole counter, ready to transmute any available wisdom into legible form—or to order more tea for the resident sage, an ancient cat known as Søren Furrygaard. The air hums with the scent of contemplation and freshly pressed hems, punctuated by the gentle ticking of an unassuming cuckoo clock, which dispenses advice instead of cooing at timely intervals.\n\n**[Signature Products/Services]**\n\nPants & Philosophy is celebrated for its \"Trouser Tête-à-Tête,\" an elaborate service where patrons can discuss life's great mysteries while being expertly fitted with a pair of multiverse-inspired trousers. These trousers, each uniquely designed to reflect the ever-shifting labyrinths of human thought, range from 299 to 499 Norwegian Kroner. Among the most sought-after are the \"Sartorial Solipsism Slacks\", known for their invisible stripes that only reveal themselves under moonlight, and the \"Utopian Uke Denim\", celebrated for its pockets, deep enough to hold the elusive secrets of happiness, or a sensible flask.\n\nThe shop also offers the \"Temporal Trouser Tailoring\", a bespoke service allowing patrons to extend or shorten their trousers to correspond with their own unique timelines. Customers can also indulge in a philosophical reading offered by the enigmatic Madame Pantelopsis, who uses a tape measure to divine wisdom and adjust waists in a single, graceful swoop.\n\n**[The Clientele]**\n\nPants & Philosophy attracts an eclectic clientele, from wandering scholars in search of wisdom's softer side to fashion-forward philosophers seeking to align their chakras with their hemlines. On any given day, you might encounter Professor Fjelldal, renowned for his theories on the elasticity of time, browsing through a selection of reflective chinos. Or perhaps you’ll meet Saga Strøm, Pjuskeby’s poet laureate, engrossed in a philosophical debate over the merits of pleats versus flat-front.\n\nFrequent patrons include the town's resident discussants, enthusiasts of both Socratic dialogue and sartorial excellence, each eager to don trousers that inspire their musings. Newcomers, drawn by the shop's elusive reputation, inevitably return, swayed by the allure of a well-fitted trouser and a mind-expanding conversation.\n\n**[Business Philosophy]**\n\nThe core philosophy of Pants & Philosophy is simple yet profound: \"Wear your thoughts on your legs, and your heart will follow.\" The establishment prides itself on fostering an environment where fashion and philosophy coalesce, where each purchase is a step closer to sartorial Nirvana. Customers are encouraged to ponder their purchases thoroughly, with staff offering guidance that strays far beyond fashion advice and into the realms of the metaphysical.\n\nIngulf Snusflatt believes that a good pair of pants can lead not just to comfort but to enlightenment, allowing individuals to stride confidently into both boardrooms and brainstorms. He often proclaims, \"Hems are horizons, and our strides are infinite.\"\n\n**[Local Reputation]**\n\nIn Pjuskeby, Pants & Philosophy has garnered a reputation that straddles legend and reality. Townsfolk spin delightful tales of trousers that granted their wearers sudden strokes of genius or heartwarming revelations. Children whisper of pants that lead wearers into alternate realities—though usually just the laundry room.\n\nKnown affectionately as \"The Sartorial Sphinx,\" the shop and its mysterious shifting location are woven into the very fabric of local folklore. Residents relish retelling their tales of finding the shop, each story a tapestry of serendipity and delight. Remarkably, despite its esoteric nature, Pants & Philosophy has yet to leave a customer unsatisfied—or without a pair of pants.\n\n---\n\nBUSINESS_KEYWORDS=pants, philosophy, trousers, tailoring, existential inquiry, sartorial enlightenment, bespoke fitting, philosophical readings\nCONTACT_INFO=Knock thrice on a birch tree | Whisper to the wind \"Legs in search of truth\" | Leave a cryptic note on a stray cat\nOPENING_HOURS=Mon-Sat: Whenever the philosophy strikes | Sundays: Only during foggy existential mornings | Thursdays: Closed for trousers in transcendental meditation\nSTATISTICS=Mystically Lost Pants:14|Philosophy Debates Per Hour:9|Sartorial Enigmas Solved:32|Invisible Stripes Discovered:6\nFUN_FACTS=Once found by following a philosophical kite | Hosted a trouser-themed think tank | Cat Søren Furrygaard has a Ph.D. in Purrlosophy | Has an entry fee of one philosophical thought | Trousers occasionally hum a tune when folded properly",
  "specialties": [],
  "established": "Unknown",
  "business_keywords": "pants, philosophy, trousers, tailoring, existential inquiry, sartorial enlightenment, bespoke fitting, philosophical readings",
  "contact_info": "Knock thrice on a birch tree | Whisper to the wind \"Legs in search of truth\" | Leave a cryptic note on a stray cat",
  "opening_hours": [
    "Mon-Sat: Whenever the philosophy strikes ",
    " Sundays: Only during foggy existential mornings ",
    " Thursdays: Closed for trousers in transcendental meditation"
  ],
  "statistics": [
    {
      "label": "Mystically Lost Pants",
      "value": "14"
    },
    {
      "label": "Philosophy Debates Per Hour",
      "value": "9"
    },
    {
      "label": "Sartorial Enigmas Solved",
      "value": "32"
    },
    {
      "label": "Invisible Stripes Discovered",
      "value": "6"
    }
  ],
  "fun_facts": [
    "Once found by following a philosophical kite ",
    " Hosted a trouser-themed think tank ",
    " Cat Søren Furrygaard has a Ph.D. in Purrlosophy ",
    " Has an entry fee of one philosophical thought ",
    " Trousers occasionally hum a tune when folded properly"
  ]
}