{
  "id": "7bb450f9-6b70-45de-ad00-1e0151cdbea9",
  "slug": "teacup-engineering-ltd",
  "name": "Teacup Engineering Ltd.",
  "type": "business",
  "address": "Unknown location",
  "category": "Shop",
  "description_short": "A unique business in Pjuskeby",
  "description_full": "**[The Establishment]**\n\nNestled somewhere inexplicably in the heart of Pjuskeby—though no one can quite point it out on a map without consulting an ancient and slightly disgruntled oaken tree—lies Teacup Engineering Ltd., a business that blends the charming absurdities of precision craftsmanship with a steaming brew of tea-infused magic. Founded by the mildly eccentric, yet impeccably punctual Gustaf Huilendrehen, the establishment began its peculiar journey when Gustaf realized that teacups have long been misunderstood. “They’re more than vessels for leaf water,” he declared to a particularly curious bumblebee, “they're gateways to pocket universes!”\n\nIn an epic quest to elevate the humble teacup, Gustaf spent his youth gathering fragments of broken porcelain and whispers of forgotten know-how from clocks that no longer tell time. Teacup Engineering Ltd. officially came to life one fog-laden morning when the first rays of dawn refracted through Gustaf’s bifocals and illuminated his masterpiece: a teacup that brewed its own storms and calmed its own tempests.\n\nSince then, the establishment has become shrouded in mystery, both for its elusive location and its enigmatic offerings. While the shop's exact address remains unknown, those who wander the cobblestoned streets of Pjuskeby will find themselves drawn to it by an unexplained, comforting aroma of bergamot and earl grey.\n\n**[The Shop Interior]**\n\nVenturing inside Teacup Engineering Ltd. is much like entering a clockwork warren designed by a particularly whimsical architect with a penchant for the improbable. The shop is a delightful labyrinth of wooden beams, brass cogs, and the soft ticking of hundreds of mismatched timepieces that paradoxically march to their own rhythms, yet harmonize in a symphony of delightful chaos.\n\nEvery available surface—walls, ceilings, and even the occasional unsuspecting customer—showcases floating shelves filled with teacups of all conceivable shapes and dimensions. Overhead, gears of varying sizes pirouette gracefully, driven not by electricity or wind, but by the ambient hum of whispered excitement exchanged amongst the patrons.\n\nThe lighting is provided by lanterns with shades made from finely cut teabag wrappers, casting a warm and inviting glow. The air is lightly spiced with the scent of cinnamon and adventure, a fitting tribute to the explorative spirit that Gustaf has infused into every fiber of the place.\n\n**[Signature Products/Services]**\n\nTeacup Engineering Ltd. is renowned for its Signature Tempest Teacups, each a meticulously crafted paradigm of both utility and wonder. These teacups can brew entire thunderstorms in their depths, with miniature lightning elegantly spiraling through the herbal mists—a perfect accompaniment to any existential contemplation. The prices of these masterpieces range from 72 herringbones to a particularly evocative tune hummed in perfect pitch, depending on the complexity of the weather desired within.\n\nAlso notable are their Whimsy Wobble Saucers, which employ a patented Gustafian design that renders them unspillable, even when teetering precariously on the edge of logic itself. They retail for precisely 13.5 giggles, with a discount offered on days where the clouds seem more like sheep than usual.\n\nLastly, the shop offers Enchanted Infusion Kits, tailored to conjure dreams or dispel doldrums, available at a negotiable rate of two verses of a nigh-forgotten lullaby.\n\n**[The Clientele]**\n\nThe clientele of Teacup Engineering Ltd. is a motley assembly of dreamers, tinkerers, and perplexed tourists who somehow stumbled upon the place while searching for meaning in their morning toast. Local inventors frequent the shop to seek inspiration or recalibrate their thinking over a brewing storm, while poets come to sip ideas from the swirling depths of Gustaf's creations.\n\nThen there are the seasoned residents of Pjuskeby, who understand that Teacup Engineering is less a store and more a communal hub for shared curiosity. Even on the most ordinary of Wednesdays, the shop buzzes with unbridled excitement as patrons trade stories about their latest cup-induced revelations.\n\n**[Business Philosophy]**\n\nAt the heart of Teacup Engineering Ltd. lies a simple yet profound philosophy: every ordinary object holds the potential for extraordinary possibilities. Gustaf firmly believes that with a sprinkle of ingenuity and a dash of whimsy, even the most mundane items can transcend their apparent limitations.\n\nThis guiding principle manifests in every corner of the establishment, where customers are encouraged to embrace the unpredictable and revel in the absurdity of life. The shop thrives on the notion that the world is a teacup—and inside, storms and serenity coexist in delicate balance.\n\n**[Local Reputation]**\n\nAmong the townsfolk of Pjuskeby, Teacup Engineering Ltd. is the subject of fond anecdotes and whispered legends. “It’s the place where I found my muse,” says Dagmar Svensdóttir, the town’s renowned inventor of musical thunderstorms. Meanwhile, Ingeborg Frimstadel swears by the transformational power of the teacups, claiming they helped her tulips bloom in the middle of winter.\n\nEven those who’ve never set foot inside speak of the shop with an inexplicable yet undeniable fondness. “Their teacups are like small miracles,” nods Elder Snorri, the local historian, “and once you’ve encountered one, you’re never quite the same.” In Pjuskeby, Teacup Engineering Ltd. isn’t just a shop—it's a portal to another world.\n\nBUSINESS_KEYWORDS=mechanical teacups, enchanted saucers, storm brewing, whimsical designs, clockwork engineering\nCONTACT_INFO=Send a letter via the breeze that whispers through the oaks\nOPENING_HOURS=Mon-Fri: When the morning fog lifts|Weekends: During the hour of improbable occurrences|Wednesdays: Tea-for-two-time\nSTATISTICS=Whimsy Customers Served:821|Teacups That Giggled:409|Cloud Conversions:17|Saucers That Wobbled:123\nFUN_FACTS=Once brewed a teacup hurricane|Inspired a song that lingers in the wind|Shop greets you with a bowing doorknob|Gustaf’s beard never gets wet|Ceiling occasionally rains sugar cubes",
  "specialties": [],
  "established": "Unknown",
  "business_keywords": "mechanical teacups, enchanted saucers, storm brewing, whimsical designs, clockwork engineering",
  "contact_info": "Send a letter via the breeze that whispers through the oaks",
  "opening_hours": [
    "Mon-Fri: When the morning fog lifts",
    "Weekends: During the hour of improbable occurrences",
    "Wednesdays: Tea-for-two-time"
  ],
  "statistics": [
    {
      "label": "Whimsy Customers Served",
      "value": "821"
    },
    {
      "label": "Teacups That Giggled",
      "value": "409"
    },
    {
      "label": "Cloud Conversions",
      "value": "17"
    },
    {
      "label": "Saucers That Wobbled",
      "value": "123"
    }
  ],
  "fun_facts": [
    "Once brewed a teacup hurricane",
    "Inspired a song that lingers in the wind",
    "Shop greets you with a bowing doorknob",
    "Gustaf’s beard never gets wet",
    "Ceiling occasionally rains sugar cubes"
  ]
}