{
  "id": "5fa688b6-3132-4710-84b0-394e2a4ea151",
  "slug": "the-toad-bakery",
  "name": "The Toad Bakery",
  "type": "business",
  "address": "Unknown location",
  "category": "Shop",
  "description_short": "A unique business in Pjuskeby",
  "description_full": "**[The Establishment]**\n\nNestled somewhere between the whispering pines and a particularly indecisive brook, The Toad Bakery is a Pjuskeby legend cloaked in culinary mystery. Much like the frogs that occasionally take up residence in its eaves, this bakery appears and disappears with the rhythm of local belief. Said to have been founded by an enigmatic baker known only as Commander Croissant, who arrived in Pjuskeby with flour-dusted boots and an obsession with amphibians, the bakery’s origins are as murky as the ponds that dot the Nordic landscape.\n\nIt's whispered in town that Commander Croissant had once been a celebrated pastry chef in Paris, who abandoned the city of lights for the tranquility of Pjuskeby after a particularly vivid dream in which a colossal toad prescribed him the secret to perfect puff pastry. True or not, patrons find themselves drawn to The Toad Bakery as much for its mystery as for its delicacies. When attempting to locate the bakery, those who swear they’ve found it report following a peculiar scent—part cinnamon, part morning mist, with just a hint of cryptic destiny.\n\n**[The Shop Interior]**\n\nStepping inside The Toad Bakery feels like being enveloped in a warm hug from a grandmother who just happens to bake in a forest glen. The air is thick with the comforting aroma of fresh bread and the occasional croak from one of the resident toads that have made their home in nooks and crannies designed specifically for their comfort. The walls, a soft mossy green, are dotted with portraits of famous historical figures—each, for some inexplicable reason, depicted with toad companions.\n\nAlongside the counter is an old wooden display case filled with pastries that seem almost too beautiful to eat, their surfaces glistening under the gentle luminescence of willow wisp chandeliers. The floors are made of uneven cobblestones that tap a melodic rhythm against one’s footfalls, as though welcoming each step with a hidden song. Charcoal etchings of distant fjords and fairy circles adorn the walls, as if inviting customers on a journey within each slice of bread.\n\n**[Signature Products/Services]**\n\nThe pièce de résistance of The Toad Bakery is undoubtedly the Frog Prince Croissants, which are somehow both buttery and enchanted, filled with a secret green filling speculated to be the very essence of a toad’s daydream. Another marvel is the Ribbit Rye, a hearty bread speckled with wild seeds, said to be kissed by the morning dew. There is also the elusive Swamp Soufflé, a seasonally exclusive delicacy that has been described as tasting like \"a sunset viewed through amphibian eyes.\"\n\nOccasionally, the bakery holds whimsical baking workshops, inviting locals and wanderers alike to experiment with dough that refuses to rise unless serenaded by a frog choir. Prices here are as ephemeral as the establishment itself, often accepting payment in the form of a well-told story or a particularly convincing frog impression.\n\n**[The Clientele]**\n\nThe Toad Bakery attracts a diverse array of clientele, from the curious tourists who have followed whispered tales through the fjords, to the local wizards who find the establishment's baked goods perfect for spell-infused picnics. Its most loyal patrons, though, are the Pjuskeby residents who understand that a visit is as much about nourishment of the soul as it is about the stomach. Bibliophilic badgers, singing squirrels, and even an elusive hedgehog poet have all been spotted savoring the bakery’s offerings, contributing to a panorama of fanciful fellowship.\n\nThe shop thrives on the culturati of Pjuskeby—those who value whimsy over reality, and who find in the bakery a refuge from the mundane. If one listens closely, the conversations that ripple around the tables often reflect a life philosophy found only in tangled dreamscapes and places like this.\n\n**[Business Philosophy]**\n\nThe Toad Bakery believes in the power of dough and delight. Here, baked goods are not merely sustenance; they are conduits of joy wrapped in flour and magic. Commander Croissant operates on the principle that every loaf has a story to tell and that bread capable of eliciting a smile is a success indeed. The bakery encourages a pace of life that prioritizes wonder—life is to be savored like a perfectly balanced pastry, where every bite holds the possibility of surprise.\n\nSustainability, both of the environment and of joy, is central to the bakery’s ethos. Ingredients are sourced locally, whenever possible, from fields kissed by the northern sun and gardens tended with elfin care. Impromptu poetry readings and frog serenades are frequent, infusing each day with a merry unpredictability.\n\n**[Local Reputation]**\n\nIn Pjuskeby, The Toad Bakery is a beacon of enchanting peculiarity. Townsfolk speak of it with a fondness reserved for the untamed wilds of their childhood imagination, describing it alternately as a bakery, a sanctuary, and a gateway to a softer, more whimsical world. Those who claim to have found it more than once are regarded with a reverence bordering on awe, for the bakery’s fluctuating presence is as much an art form as its confections.\n\nThe townspeople have accepted that The Toad Bakery exists on its own terms, emerging from the mists when the world most needs a touch of magic. It is, they say, the truest embodiment of Pjuskeby spirit—a reminder that the line between the extraordinary and the everyday is as thin and sweet as a sprinkle of icing sugar.\n\nBUSINESS_KEYWORDS=fresh bread, pastries, magical baking, enchanted ingredients, local workshops  \nCONTACT_INFO=Leave a breadcrumb trail through the forest  \nOPENING_HOURS=Mon-Fri: When the fog lifts|Weekends: During a toad’s nap time|Thursdays: If the sun winks thrice  \nSTATISTICS=Frog Songs Per Hour:9|Croissants Transcended:32|Toad Tea Parties Hosted:47|Unexplained Laughs:123  \nFUN_FACTS=Bread occasionally recites limericks|The owner wears a crown of dandelions|Tadpoles once baked a cake|Swamp Soufflé recipe is locked in a lily pad vault|Floors hum a lullaby at midnight",
  "specialties": [],
  "established": "Unknown",
  "business_keywords": "fresh bread, pastries, magical baking, enchanted ingredients, local workshops  ",
  "contact_info": "Leave a breadcrumb trail through the forest  ",
  "opening_hours": [
    "Mon-Fri: When the fog lifts",
    "Weekends: During a toad’s nap time",
    "Thursdays: If the sun winks thrice  "
  ],
  "statistics": [
    {
      "label": "Frog Songs Per Hour",
      "value": "9"
    },
    {
      "label": "Croissants Transcended",
      "value": "32"
    },
    {
      "label": "Toad Tea Parties Hosted",
      "value": "47"
    },
    {
      "label": "Unexplained Laughs",
      "value": "123"
    }
  ],
  "fun_facts": [
    "Bread occasionally recites limericks",
    "The owner wears a crown of dandelions",
    "Tadpoles once baked a cake",
    "Swamp Soufflé recipe is locked in a lily pad vault",
    "Floors hum a lullaby at midnight"
  ]
}