{
  "id": "0b80bdbc-6257-4797-abc6-c0e899dd9bd9",
  "slug": "the-department-of-lost-echoes",
  "name": "The Department of Lost Echoes",
  "type": "business",
  "address": "Unknown location",
  "category": "Shop",
  "description_short": "A unique business in Pjuskeby",
  "description_full": "**[The Establishment]**\n\nThe Department of Lost Echoes is a curious establishment nestled somewhere in the twisting lanes of Pjuskeby, though its precise location remains one of the town's many mysteries. The shop, or rather, the concept of it, started on a misty midsummer's eve when the enigmatic founder, Thorfinn Whisperingwind, realized that echoes, like memories, needed a place to rest when lost. He was an eccentric gentleman, prone to unusual epiphanies and passionate about the ambient murmurs that float on the edges of perception.\n\nThorfinn opened the Department to collect and catalog these stray sound waves: the laughter of children forgotten in time, whispers of the wind too shy to be heard, and melodies of songs left unfinished. Rather than selling conventional goods, the Department acts as a shelter for these vagabond sounds, preserving and occasionally purveying them to those who know how to listen.\n\n\n**[The Shop Interior]**\n\nStepping inside the Department of Lost Echoes is akin to entering a realm where sound and silence dance a slow waltz. The shop is delightfully cluttered with an assemblage of mismatched furniture and whimsical decor. The walls, an indeterminate shade that flickers between twilight blue and early morning gray, seem to hum softly, as if tuning themselves to the patrons' moods. \n\nAn old phonograph sits in a corner, its horn gently spinning ethereal tunes that no one remembers recording. Shelves are laden with peculiar glass bottles, each containing a shimmering echo, labeled with tags like \"Fishwife's Call, 1897\" or \"Winter's Breath Over Fjord, 1923.\" The air itself seems thoughtfully tangled, carrying a perpetual scent of pine needles and distant thunder.\n\n\n**[Signature Products/Services]**\n\nThe Department is known for its bespoke Echo Bottling Service, wherein patrons bring their own sounds to be distilled and bottled. Prices for bottling vary wildly, from a modest 17 krone for a single sigh to an extravagant 212 krone for the full orchestral experience of a summer rainstorm. Another popular service is the Echo Matching Consultation, during which Thorfinn himself, or his apprentice Solveig Softwhisper, helps customers find the echo that resonates with their soul. No appointment needed—just the willingness to wait until the echo finds you.\n\nOne cannot leave without experiencing the Echo Chamber, a plush padded alcove where patrons can sit, close their eyes, and be enveloped in a cascade of nostalgic reverberations, from the cheery clink of an old ice cream truck to the hushed whispers of first love.\n\n\n**[The Clientele]**\n\nThe Department's clientele is a motley crew. Local poets frequent the shop to find the perfect echo to inspire their verses, while retired fishermen seek the familiar lull of the sea they long sailed upon. Occasionally, a curious tourist stumbles in, mistaking the establishment for a local museum, only to leave with a consonant of a sound they never knew they needed.\n\nEccentric artists, sound collectors, and introspective philosophers are often found huddled in animated discussions, debating the merits of a perfectly preserved echo of a waterfall versus the unruly allure of a thunderclap. Children, too, visit, bringing fledgling sounds they hope to nurture, and elder villagers come to rediscover the gentle coo of their long-lost youth.\n\n\n**[Business Philosophy]**\n\nAt the heart of the Department of Lost Echoes is the belief that sound is the tether of memory. Each echo is a narrative, a fragment of time, and the establishment strives to preserve this delicate anthology of human experience. Thorfinn Whisperingwind maintains that echoes are the fingerprints of moments, and by capturing them, one honors their ephemeral beauty.\n\nThe shop operates on the philosophy that every sound deserves a listener. Echoes are not commodities but companions, and the Department prides itself on matching them with those who need them most. Thorfinn’s motto, stitched onto a tapestry behind the counter, reads: \"In the whisper of the wind, find the heartbeat of the world.\"\n\n\n**[Local Reputation]**\n\nAmong the townspeople of Pjuskeby, The Department of Lost Echoes is spoken of in hushed tones and with affectionate reverence. It's as much a part of the community as the fjord’s gentle ebb and flow. For many, it's a sanctuary of sorts—where the past meets the present in a symphony of sound.\n\nRumors abound of the shop's magical qualities, claiming that the echoes, once heard, can heal old wounds and spark new dreams. Despite, or perhaps because of, its secrecy and eccentricity, the Department remains a beloved enigma, like a sweet, haunting refrain that lingers long after the music has ended.\n\nVillagers often recount tales of Thorfinn’s uncanny ability to match an echo to a person's deepest longing, and there’s a shared understanding that those who find the Department discover more than mere echoes—they find pieces of themselves.\n\nBUSINESS_KEYWORDS=echo bottling, sound preservation, acoustic sanctuary, sound matching, echo chamber\nCONTACT_INFO=Put a seashell to your ear and whisper your request\nOPENING_HOURS=Mon-Fri: Whenever the silhouette of the moon smiles|Weekends: When the pine trees sigh in unison|Thursdays: Closed for the annual echo inventory reverb\nSTATISTICS=Echoes Bottled:732|Pine Needle Scent: Perpetual|Thunderous Applause Moments:57|Epiphanies Born:104\nFUN_FACTS=Once contained the sound of a dragon's sneeze|All echoes are tickled pink daily|Named best lost sound shop three years running by the Nordic Society of Sounds|Walls hum in A minor|Shop once levitated for three minutes and four seconds",
  "specialties": [],
  "established": "Unknown",
  "business_keywords": "echo bottling, sound preservation, acoustic sanctuary, sound matching, echo chamber",
  "contact_info": "Put a seashell to your ear and whisper your request",
  "opening_hours": [
    "Mon-Fri: Whenever the silhouette of the moon smiles",
    "Weekends: When the pine trees sigh in unison",
    "Thursdays: Closed for the annual echo inventory reverb"
  ],
  "statistics": [
    {
      "label": "Echoes Bottled",
      "value": "732"
    },
    {
      "label": "Pine Needle Scent",
      "value": "Perpetual"
    },
    {
      "label": "Thunderous Applause Moments",
      "value": "57"
    },
    {
      "label": "Epiphanies Born",
      "value": "104"
    }
  ],
  "fun_facts": [
    "Once contained the sound of a dragon's sneeze",
    "All echoes are tickled pink daily",
    "Named best lost sound shop three years running by the Nordic Society of Sounds",
    "Walls hum in A minor",
    "Shop once levitated for three minutes and four seconds"
  ]
}