{
  "id": "bd013d99-0e54-466b-b008-dc9aaf093989",
  "slug": "tinkle-snort-plumbing",
  "name": "Tinkle & Snort Plumbing",
  "type": "business",
  "address": "Unknown location",
  "category": "Shop",
  "description_short": "A unique business in Pjuskeby",
  "description_full": "**[The Establishment]**\n\nTinkle & Snort Plumbing is the most elusive business in Pjuskeby—a town already brimming with enchantingly elusive establishments. Its precise location is an enigmatic riddle left on the lips of every resident, whispered only to those who claim to have found it. Founded in 1965 by two wandering plumbers, Pjorn Tinkle and Sven Snort, the business brandishes on its phantom sign an unlikely blend of humor and function. The story began when Pjorn accidentally invented self-cleaning pipes while attempting to distill moonlight into his grandmother's potato soup recipe. Sven, an ex-juggler-turned-hydraulic-engineer, happened upon Pjorn while both were arguing with a particularly polite gnome over local sponge taxes. Joining forces felt like the next logical step.\n\nThey became renowned for their unconventional approach to plumbing, which included musical pipes that hummed folk tunes from forgotten lands and toilets that whispered sweet nothings to alleviate any potential embarrassment. While a secretive establishment, its presence is assured by the occasional sighting of merry patrons clutching shiny new faucets or enchanted plungers as they disappear into the mist.\n\n\n**[The Shop Interior]**\n\nUpon the rare occasion one stumbles into Tinkle & Snort Plumbing, it feels less like entering a store and more like an excursion into a forgotten fairytale. The shop, if it can be called that, appears as an ancient hollow oak tree. Inside, its cavernous interior is unexpectedly spacious and gleams warmly like the setting sun reflecting off a bubbling brook. The flooring is a patchwork of reclaimed tiles, each telling its own absurd story—like the one from Mrs. Flibberflap's kitchen where three invisible mice once held a tea party.\n\nCopper pipes in every conceivable shape form a serpentine canopy, creating an acoustic wonderland where each footstep reverberates in melodic chimes. On the walls rest beautifully chaotic schematics for projects never intended to work, alongside rustically charming shelves crammed with objects that appear more curious than plumbing-specific at first glance. There, nestled between leaky bathtubs with rainbows arching over them, rests an assortment of comically large wrenches and spigots disguised as woodland creatures.\n\n\n**[Signature Products/Services]**\n\nTinkle & Snort Plumbing specializes in the whimsical world of whimsical plumbing. They are most famous for their \"Pipes of Merriment,\" which not only transport water but also one's spirit to a place of unexpected joy. These pipes, crafted lovingly from a blend of Nordic spruce and enchanted copper, play traditional Norwegian melodies every time water flows through them—an instant hit with Pjuskeby's poetry clubs.\n\nAnother renowned item is the \"Chortle Flange.\" Used primarily for mischief, this flange creates giggles that echo through the home at random intervals. The \"Once-in-a-Blue-Moon Faucet\" is highly sought after, dispensing moonlit water favored by insomniacs and poets who dabble in night-time gardening.\n\nTheir services include anything from the imaginative \"Berserker Boiler Repairs,\" during which, so legend has it, runic chants are sung to appease the boiler's fiery temperament, to the \"Elegy for Eavestroughs,\" a solemn ceremony ensuring complete seasonal functionality—guaranteed to sound beautiful even in the gloomiest of rain.\n\n\n**[The Clientele]**\n\nThe clientele of Tinkle & Snort Plumbing is as eclectic as the town of Pjuskeby itself. They include eccentric inventors with a penchant for geysers-in-miniature, local wizards seeking to imbue their cauldrons with extra fizz, and grandmothers with a yen for adventure who just want their sinks to occasionally exhale the fragrance of cinnamon buns.\n\nOn any given day, one might find visiting elves picking out decorative taps (elves deeply value aesthetic, after all) or a disoriented hiker who swears he just followed the aroma of fresh pine. However, it is the town's own Mayor Windwhiffle, notorious for his collection of animated water sculptures, who is perhaps Tinkle & Snort's staunchest supporter. His recent acquisition, the \"Giggling Geyser,\" now graces the town square, gushing laughter at precisely noon every day.\n\n\n**[Business Philosophy]**\n\nThe philosophy of Tinkle & Snort is a jubilant embrace of the unconventional. Plumbing, they argue, should not merely be about function but about embracing whimsy and sparking delight. Their motto, \"Where Water Meets Wonder,\" encapsulates their belief that every drip, gush, and sprinkle should bring surprise and joy. They maintain that plumbing is no mere trade—it's a theatre of the absurd, with every fixture a potential character in the play of life.\n\nTheir playful methodology is evident in their commitment to sustainability—using materials enchanted to last several lifetimes while singing lullabies to frogs. Even the rare scheduled service interruption is turned into an occasion; it's not uncommon for Pjorn and Sven to declare a \"Plumber's Picnic,\" filled with stories, laughter, and the occasional unsolicited fortune-telling by the spryer of their pipes.\n\n\n**[Local Reputation]**\n\nIn Pjuskeby, Tinkle & Snort Plumbing is as much a legend as it is a mystery. Townspeople speak of the shop as a revered institution, though few admit to having ever physically visited. Whispers of its magic dance through the air of tavern conversations and elderly knitting circles alike.\n\nChildren often talk of \"Tinkle & Snort\" as a magical place where water balloons float instead of fall, and intern plumbing apprentices recount tales of apprenticeships that happened, curiously enough, only in dreams. While some pragmatic locals dismiss its existence as pure folklore, they can't deny the curious phenomena of unattended leaks turning into orchestrated water concerts.\n\nIts reputation is underscored by the unwritten agreement of amazement—within Pjuskeby, ignoring the logically inexplicable in favor of the enchantingly inexplicable is not a suggestion, but a way of life. Those who claim to have met Pjorn and Sven describe them as both there and not there—a sentiment that echoes the ethos of Tinkle & Snort Plumbing itself.\n\nBUSINESS_KEYWORDS=musical pipes, enchanted faucets, giggling plungers, whimsical repairs, magical plumbing  \nCONTACT_INFO=Send a smoke signal in the shape of a leaky faucet  \nOPENING_HOURS=Thursdays: Whenever the moon's in a jovial mood|Sundays: Upon the third yawn of the village cat|Wednesdays: Closed unless the wind whispers secrets  \nSTATISTICS=Melodies Per Installation:7|Invisible Mice Tea Parties:3|Plumber's Picnics Held:5|Giggling Geysers Installed:12  \nFUN_FACTS=Once fixed a leak that sang opera|Tools include a self-aware wrench named Wrenchie|Once served tea to a talking pipe|Faucets often tell bedtime stories|Toilets sometimes apologize for the noise",
  "specialties": [],
  "established": "Unknown",
  "business_keywords": "musical pipes, enchanted faucets, giggling plungers, whimsical repairs, magical plumbing  ",
  "contact_info": "Send a smoke signal in the shape of a leaky faucet  ",
  "opening_hours": [
    "Thursdays: Whenever the moon's in a jovial mood",
    "Sundays: Upon the third yawn of the village cat",
    "Wednesdays: Closed unless the wind whispers secrets  "
  ],
  "statistics": [
    {
      "label": "Melodies Per Installation",
      "value": "7"
    },
    {
      "label": "Invisible Mice Tea Parties",
      "value": "3"
    },
    {
      "label": "Plumber's Picnics Held",
      "value": "5"
    },
    {
      "label": "Giggling Geysers Installed",
      "value": "12"
    }
  ],
  "fun_facts": [
    "Once fixed a leak that sang opera",
    "Tools include a self-aware wrench named Wrenchie",
    "Once served tea to a talking pipe",
    "Faucets often tell bedtime stories",
    "Toilets sometimes apologize for the noise"
  ]
}