{
  "id": "a160a6b9-f150-4a0f-8c0b-0325c338237b",
  "slug": "whisker-bazaar",
  "name": "Whisker Bazaar",
  "type": "business",
  "address": "Unknown location",
  "category": "Shop",
  "description_short": "A unique business in Pjuskeby",
  "description_full": "**[The Establishment]**\n\nWhisker Bazaar emerged from the mists of obscurity on a day when the Northern Lights were practicing their dance routines at noon, shattering all preconceived notions about light and time. Nestled somewhere within the topsy-turvy streets of Pjuskeby, this elusive establishment has no fixed address. Instead, it appears wherever it's needed most—on corners where whispers gather, or at crossroads frequented by cats with a mysterious gleam in their eyes. Founded by the enigmatic Lars Tjottblom, a former whisper-tamer, the Bazaar specializes in providing Pjuskeby’s inhabitants with everything feline—not objects, but whispers. Lars’ fascination with whispers began when he overheard a cat conspiring with the wind. He decided to curate a collection of whispers that could rival any library of books.\n\n**[The Shop Interior]**\n\nUpon locating the Bazaar—which typically involves following a tabby with particularly expressive whiskers—you step into a realm where whispers cavort and pirouette like invisible ballet dancers. The air vibrates with a gentle murmur, each sound an invitation to eavesdrop on the universe’s secrets. Shelves are stacked with jars containing whispers labeled with titles like \"Elderberry Secrets of 1902\" and \"Midnight Confessions of the Moon.\" The walls are an amalgamation of cat fur and stardust, giving them a soft, velvety texture that hums a gentle lullaby whenever someone sneezes. Lanterns cast a warm, golden glow, creating a cozy, otherworldly atmosphere reminiscent of an ancient Nordic myth whistling through a forest.\n\n**[Signature Products/Services]**\n\nWhisker Bazaar is famed for its signature product: bottled cat whisker whispers. These whispers are carefully harnessed during the feline solstice, a time when cats gather in Pjuskeby’s imaginary amphitheater to meow their most profound musings into the breeze. The whispers are meticulously bottled and sold for 42 Norwegian Krone each, ensuring everyone can afford a sprinkle of clandestine wisdom. Among the most popular selections are \"Springtime Hopes from the Tabby Clan\" and \"Regal Thoughts of Duchess Meowington III.\" For the more adventurous whisper-seekers, Lars offers custom-blended whispers, tailored to your taste and mood. These are crafted using a rare blend of Siberian tiger snuffles and the sighs of an elusive Arkticfeline Dragon, available by appointment only.\n\n**[The Clientele]**\n\nThe Bazaar attracts an eclectic mix of clients, ranging from earnest poets, who seek inspiration from the cryptic charms contained within, to local fishermen, hoping to harness the secrets of the seas hidden in a tabby’s purr. You might encounter Professor Antsje Plufferpuff, who insists on wearing a cape woven from her own beard, or Minerva Clinklefritz, known for her perpetual dandelion tiara and belief that whispers can be baked into bread. Children occasionally find their way here, guided by invisible strings of curiosity, and leave with pockets full of laughter-inducing whispers that make their pet hamsters chatter through the night. \n\n**[Business Philosophy]**\n\nAt the heart of Whisker Bazaar is a simple yet profound philosophy: whispers shape reality. Lars believes that the world is spun from the ethereal threads of secrets and dreams, and by sharing these fragments, the Bazaar helps weave a more whimsical world. The shop operates on the principle that whispers belong to everyone, and as such, any whisper can be exchanged for another of equal value, or even for a particularly intriguing story, as stories are the currency of the heart.\n\n**[Local Reputation]**\n\nTownspeople often speak of Whisker Bazaar in hushed tones, as if the mere mention could summon it to their doorstep. \"Like a will-o'-the-wisp in cat form,\" they say, referencing its elusive nature. Mayor Flannelstrom once attributed the unusual peace between the town's sparrows and cats to a diplomatic whisper purchased from the Bazaar, leading to the coining of the phrase, \"As harmonious as a Whisker Bazaar treaty.\" Its legends are as varied as the whispers it houses; some claim that the Bazaar only opens during moonlit snowfalls, while others swear it's the only place to hear a dragon sneeze.\n\nBUSINESS_KEYWORDS=whispers, feline secrets, bottled musings, cat whiskers, invisible ballet\nCONTACT_INFO=Whistle three times into the northern wind and wait\nOPENING_HOURS=Mon-Fri: When the moon is napping|Weekends: Upon the third meow|Tuesdays: During time's lunch break\nSTATISTICS=Mysterious Whispers Bottled:1089|Cats Consulted:432|Sneezes Recorded:206|Midnight Meetings:77\nFUN_FACTS=Once eavesdropped on the moon|Cats howl in harmony every Thursday|The floorboards are enchanted with ticklish spells|Inventor of the whispering tea kettle|Occasionally open backward in time",
  "specialties": [],
  "established": "Unknown",
  "business_keywords": "whispers, feline secrets, bottled musings, cat whiskers, invisible ballet",
  "contact_info": "Whistle three times into the northern wind and wait",
  "opening_hours": [
    "Mon-Fri: When the moon is napping",
    "Weekends: Upon the third meow",
    "Tuesdays: During time's lunch break"
  ],
  "statistics": [
    {
      "label": "Mysterious Whispers Bottled",
      "value": "1089"
    },
    {
      "label": "Cats Consulted",
      "value": "432"
    },
    {
      "label": "Sneezes Recorded",
      "value": "206"
    },
    {
      "label": "Midnight Meetings",
      "value": "77"
    }
  ],
  "fun_facts": [
    "Once eavesdropped on the moon",
    "Cats howl in harmony every Thursday",
    "The floorboards are enchanted with ticklish spells",
    "Inventor of the whispering tea kettle",
    "Occasionally open backward in time"
  ]
}